banner/__init__.py
banner/admin.py
banner/api.py
banner/api_urls.py
banner/apps.py
banner/models.py
banner/processors.py
banner/serializers.py
banner/test_api.py
banner/tests.py
banner/urls.py
banner/views.py
banner/migrations/0001_initial.py
banner/migrations/0002_auto_20180523_1735.py
banner/migrations/0003_auto_20180607_1054.py
banner/migrations/0004_banner_order.py
banner/migrations/0005_auto_20190114_1708.py
banner/migrations/0006_auto_20190114_1710.py
banner/migrations/0007_banner_image_url.py
banner/migrations/0008_banner_code_mobile.py
banner/migrations/0009_banner_valid_until.py
banner/migrations/0010_auto_20200428_1232.py
banner/migrations/0011_alter_banner_position_bannerviews_bannertotalclicks_and_more.py
banner/migrations/0012_banner_mobile_image_banner_small_mobile_image.py
banner/migrations/__init__.py
banner/static/banner/admin-banner.js
banner/static/banner/banner.js
banner/static/banner/banner.min.js
banner/static/banner/js/admin-banner.js
banner/static/banner/js/post-admin.js
banner/static/js/post-admin.js
banner/templates/admin/banner/change_form.html
banner/templates/banner/banner.html
banner/templates/banner/banner_bottom.html
banner/templates/banner/banner_content.html
banner/templates/banner/banner_redirect.html
banner/templates/banner/banner_skyscraper_left.html
banner/templates/banner/banner_skyscraper_right.html
banner/templates/banner/banner_top.html
banner/templates/banner/post_detail_banner_bottom.html
banner/templates/banner/post_detail_banner_content.html
banner/templates/banner/post_detail_banner_skyscraper_left.html
banner/templates/banner/post_detail_banner_skyscraper_right.html
banner/templates/banner/post_detail_banner_top.html
banner/templatetags/custom_tags.py
django_reaktion_banner-0.0.8.dist-info/LICENSE
django_reaktion_banner-0.0.8.dist-info/METADATA
django_reaktion_banner-0.0.8.dist-info/WHEEL
django_reaktion_banner-0.0.8.dist-info/top_level.txt
django_reaktion_banner-0.0.8.dist-info/RECORD
